LICENSE.txt
MANIFEST.in
README.rst
pavement.py
requirements.txt
setup.py
docs/conf.py
docs/gtkwave_output.vcd
docs/index.rst
docs/readme.rst
docs/usage.rst
sphinxcontrib/__init__.py
sphinxcontrib/gtkwave.py
sphinxcontrib_gtkwave.egg-info/PKG-INFO
sphinxcontrib_gtkwave.egg-info/SOURCES.txt
sphinxcontrib_gtkwave.egg-info/dependency_links.txt
sphinxcontrib_gtkwave.egg-info/namespace_packages.txt
sphinxcontrib_gtkwave.egg-info/not-zip-safe
sphinxcontrib_gtkwave.egg-info/requires.txt
sphinxcontrib_gtkwave.egg-info/top_level.txt